paged_index_downloader/__init__.py
paged_index_downloader/base.py
paged_index_downloader/pipelines.py
paged_index_downloader-0.0.14.dist-info/LICENSE
paged_index_downloader-0.0.14.dist-info/METADATA
paged_index_downloader-0.0.14.dist-info/WHEEL
paged_index_downloader-0.0.14.dist-info/top_level.txt
paged_index_downloader-0.0.14.dist-info/RECORD
