Metadata-Version: 2.1
Name: paged-index-downloader
Version: 0.0.14
Summary: A way to easily download news listings using Scrapy
Author-email: Alex Thompson <alexthompson1991@hotmail.com>
Classifier: Programming Language :: Python :: 3
Classifier: License :: OSI Approved :: MIT License
Classifier: Operating System :: OS Independent
Requires-Python: >=3.7
License-File: LICENSE
